{
  "_class": "shapePath",
  "booleanOperation": -1,
  "do_objectID": "B8ADC609-D8D1-4FAB-BCCA-2F04680BA3A2",
  "edited": true,
  "exportOptions": {
    "_class": "exportOptions",
    "exportFormats": [
    ],
    "includedLayerIds": [
    ],
    "layerOptions": 0,
    "shouldTrim": false
  },
  "frame": {
    "_class": "rect",
    "constrainProportions": false,
    "height": 6.264430344827589,
    "width": 5.00756020942409,
    "x": 11.43551832460798,
    "y": 6.906769655172415
  },
  "isFlippedHorizontal": false,
  "isFlippedVertical": false,
  "isLocked": false,
  "isVisible": true,
  "layerListExpandedType": 0,
  "name": "Path",
  "nameIsFixed": false,
  "path": {
    "_class": "path",
    "isClosed": true,
    "pointRadiusBehaviour": 0,
    "points": [
      {
        "_class": "curvePoint",
        "cornerRadius": 0,
        "curveFrom": "{0.098489822718317965, 0.38503366131538064}",
        "curveMode": 4,
        "curveTo": "{0, 0}",
        "hasCurveFrom": true,
        "hasCurveTo": false,
        "point": "{0, 0}"
      },
      {
        "_class": "curvePoint",
        "cornerRadius": 0,
        "curveFrom": "{0.71667760998030283, 0.73588814085965837}",
        "curveMode": 4,
        "curveTo": "{0.25607353906762953, 0.72345934748834806}",
        "hasCurveFrom": true,
        "hasCurveTo": true,
        "point": "{0.48456992777412866, 1}"
      },
      {
        "_class": "curvePoint",
        "cornerRadius": 0,
        "curveFrom": "{1, 0}",
        "curveMode": 4,
        "curveTo": "{0.90183847669074002, 0.4005696530295183}",
        "hasCurveFrom": false,
        "hasCurveTo": true,
        "point": "{1, 0}"
      }
    ]
  },
  "resizingConstraint": 63,
  "resizingType": 0,
  "rotation": 0,
  "shouldBreakMaskChain": false
}